spotlight/__init__.py
spotlight/config.py
spotlight/errors.py
spotlight/exceptions.py
spotlight/rules.py
spotlight/utils.py
spotlight/validator.py
spotlight-3.2.0.dist-info/LICENSE
spotlight-3.2.0.dist-info/METADATA
spotlight-3.2.0.dist-info/WHEEL
spotlight-3.2.0.dist-info/top_level.txt
spotlight-3.2.0.dist-info/RECORD
