Metadata-Version: 2.1
Name: spotlight
Version: 3.2.0
Summary: Data validation for Python, inspired by the Laravel framework.
Home-page: https://github.com/mdoesburg/spotlight
Author: Michiel Doesburg
Author-email: michiel@moddix.com
License: MIT
Project-URL: Documentation, https://github.com/mdoesburg/spotlight
Project-URL: Code, https://github.com/mdoesburg/spotlight
Keywords: spotlight validation validate
Platform: UNKNOWN
Requires-Python: >=3.6
License-File: LICENSE
